{
    "TPHAOU": "néo-{^}",
    "SPWEU": "anti-{^}",
    "AO*T" :"auto-{^}",
    "R-" : "re{^}",
    "SP*R" : "super-{^}",
    "PHU*LT" : "multi-{^}", 
    "SKO*E" : "psycho{^}",
    "A*GS" : "{^ation}", 
    "TPHEUFPL": "{^nisme}",
    "-R" : "{^er}",
    "-L": "{=(?i)[aâàeéêiouyh]/l'/le }{^}",
    "-PL": "{=(?i)[aâàeéêiouyh]/m'/me }{^}",
    "T": "{=(?i)[aâàeéêiouyh]/t'/te }{^}",  
    "SKWR": "{=(?i)[aâàeéêiouyh]/j'/je }{^}",
    "K": "{=(?i)[aâàeéêiouyh]/qu'/que }{^}",
    "P-BG": "{=(?i)[aâàeéêiouyh]/parce qu'/parce que }{^}", 
    "TK-": "{=(?i)[aâàeéêiouyh]/d'/de }{^}",
    "PHAUD": "{=(?i)[aâàeéêiouyh]/mois d'/mois de }{^}",
    "H": "{=(?i)[aâàeéêiouyh]/n'/ne }{^}",
    "PH-": "{=(?i)[aâàeéêiouyh]/m'/me }{^}" ,
    "*FS": "{^}z-vous",
    "*UT": "{^}-tu",
    "UT": "{^}s-tu",
    "+-S": "{^^^}s",   
    "OTS" : "autre",
    "KWREPS": "il n'est pas",
    "KWRAPS": "il n'y a pas",
    "KWRAB": "il n'y a",
    "H*PS": "{^nepas}",
    "-L/H*PS": "{^lenepas}",
    "-LG/H*PS": "{^lanepas}",
    "-LS/H*PS": "{^lesnepas}",
    "HA*UPS": "{^neluipas}",
    "H*PLS": "{^nemepas}",
    "H*P": "{^neplus}",
    "H*G": "{^nejamais}",

    "A*EUS": "{^ais}",
    "A*EUT": "{^ait}",
    "A*EUPBT": "{^aient}",

    "-S": "{^s}",
    "-G": "{^ant}",
    "-GT": "{^ante}",
    "-GS": "{^tion}", 
    "-D": "{^é}",
    "*E": "{^}e",  
    "-DZ": "{^ée}",
    "-GS/-*EL": "{^tionnel}"
}

